[
  {
    "id": "31087",
    "title": "Lego creator - 31087",
    "price": 9.1,
    "link": "https://www.vinted.fr/items/1943608940-lego-creator-31087",
    "published": 1654586881,
    "uuid": "a71b9552-67bd-460e-8484-08eeefb69e21"
  },
  {
    "id": "31087",
    "title": "Lego creator 3in1",
    "price": 11.2,
    "link": "https://www.vinted.fr/items/2806629865-lego-creator-3in1",
    "published": 1679240264,
    "uuid": "6534dd90-3a0e-4e27-81c7-0722f34b7a43"
  },
  {
    "id": "31087",
    "title": "Lego creator 31087",
    "price": 3.85,
    "link": "https://www.vinted.fr/items/5168017769-lego-creator-31087",
    "published": 1728214540,
    "uuid": "d1a8f25e-368e-44c4-9a4e-07f3b4507c27"
  },
  {
    "id": "31087",
    "title": "Lego 31087",
    "price": 11.2,
    "link": "https://www.vinted.fr/items/2475480622-lego-31087",
    "published": 1669975147,
    "uuid": "55243792-b03f-452b-bece-569b0db10b20"
  },
  {
    "id": "31087",
    "title": "Lego creator 31087",
    "price": 5.95,
    "link": "https://www.vinted.fr/items/5340689316-lego-creator-31087",
    "published": 1730923584,
    "uuid": "0d6a3fdb-ca6c-481e-8585-acad4364e64c"
  },
  {
    "id": "31087",
    "title": "Lego 3 en 1 31087 Buggy",
    "price": 11.2,
    "link": "https://www.vinted.fr/items/5336141066-lego-3-en-1-31087-buggy",
    "published": 1730837992,
    "uuid": "0a56483d-f104-4412-90b8-6db4bdcf7015"
  },
  {
    "id": "31087",
    "title": "Lego creator",
    "price": 7,
    "link": "https://www.vinted.fr/items/3350341149-lego-creator",
    "published": 1692026232,
    "uuid": "b352d891-0519-4709-a869-31c1d1cb7c76"
  },
  {
    "id": "31087",
    "title": "Lego creator 31087 neuf",
    "price": 13.3,
    "link": "https://www.vinted.fr/items/5234289363-lego-creator-31087-neuf",
    "published": 1729190460,
    "uuid": "146f5dde-bded-4b10-b7ea-e7893e546889"
  },
  {
    "id": "31087",
    "title": "Lego 31087",
    "price": 9.1,
    "link": "https://www.vinted.fr/items/5312289514-lego-31087",
    "published": 1730474209,
    "uuid": "dfaded98-42d8-4703-9d69-09a605e6ff68"
  },
  {
    "id": "31087",
    "title": "Lego creator 3 en 1 complet 31087",
    "price": 5.43,
    "link": "https://www.vinted.fr/items/4380842228-lego-creator-3-en-1-complet-31087",
    "published": 1713432926,
    "uuid": "9e76ab1c-88d5-4dc5-9867-2de84e6efd4a"
  },
  {
    "id": "31087",
    "title": "Lego créature 3en1 31087",
    "price": 13.3,
    "link": "https://www.vinted.fr/items/5333830483-lego-creature-3en1-31087",
    "published": 1730812208,
    "uuid": "cf9cee58-cb16-41e3-90c6-2d91dc592f4f"
  },
  {
    "id": "31087",
    "title": "Lego 31087",
    "price": 11.2,
    "link": "https://www.vinted.fr/items/5351839196-lego-31087",
    "published": 1731152909,
    "uuid": "a12c61e1-a829-48fe-adaf-3243387b7253"
  },
  {
    "id": "31087",
    "title": "Lego creator 31087  3 en 1  « Le buggy des dunes »",
    "price": 11.2,
    "link": "https://www.vinted.fr/items/5326404613-lego-creator-31087-3-en-1-le-buggy-des-dunes",
    "published": 1730665953,
    "uuid": "c979b66b-81ba-47df-bd08-6384676483c0"
  },
  {
    "id": "31087",
    "title": "Lego creator 31087",
    "price": 11.2,
    "link": "https://www.vinted.fr/items/4892251953-lego-creator-31087",
    "published": 1723752595,
    "uuid": "ec13e42d-7848-4e84-ac15-d22a9962da08"
  },
  {
    "id": "31087",
    "title": "Lego 31087",
    "price": 7,
    "link": "https://www.vinted.fr/items/5198270771-lego-31087",
    "published": 1728657075,
    "uuid": "b135681a-b60a-4d22-8480-744e03110020"
  },
  {
    "id": "31087",
    "title": "Lego 3 en 1 31087",
    "price": 5.95,
    "link": "https://www.vinted.fr/items/4871943837-lego-3-en-1-31087",
    "published": 1723312453,
    "uuid": "7aaf0e58-742d-4fa1-9142-3d26dd6e4bf2"
  },
  {
    "id": "31087",
    "title": "Lego créator 31087",
    "price": 11.2,
    "link": "https://www.vinted.fr/items/4993041263-lego-creator-31087",
    "published": 1725563631,
    "uuid": "8104c460-2f2b-4784-96e7-e41c6dcf7ea6"
  },
  {
    "id": "31087",
    "title": "Lego Creator 3 en 1 31087 Le buggy des dunes",
    "price": 7,
    "link": "https://www.vinted.fr/items/4846456053-lego-creator-3-en-1-31087-le-buggy-des-dunes",
    "published": 1722783710,
    "uuid": "453663ea-3427-4492-aa66-aefec34909a6"
  },
  {
    "id": "31087",
    "title": "Lego creator 31087 complet",
    "price": 7,
    "link": "https://www.vinted.fr/items/4588318810-lego-creator-31087-complet",
    "published": 1717332895,
    "uuid": "c78caed8-57ff-4059-a3a7-16a60345c157"
  },
  {
    "id": "31087",
    "title": "Le buggy des dunes Lego creator 31087",
    "price": 9.1,
    "link": "https://www.vinted.fr/items/5237089668-le-buggy-des-dunes-lego-creator-31087",
    "published": 1729255495,
    "uuid": "f4870fdc-20fb-4b47-a59e-825acbd4b389"
  },
  {
    "id": "31087",
    "title": "Lego 6 +. Creator. 4x4 tout terrain. Buggy. 31087",
    "price": 8.05,
    "link": "https://www.vinted.fr/items/3882038564-lego-6-creator-4x4-tout-terrain-buggy-31087",
    "published": 1702563602,
    "uuid": "bc64beca-4f37-4819-a683-450ca44de147"
  },
  {
    "id": "31087",
    "title": "Lego Creator 31087",
    "price": 5.95,
    "link": "https://www.vinted.fr/items/5232435474-lego-creator-31087",
    "published": 1729171061,
    "uuid": "f5086807-94b7-4bdb-88fe-ccb269f542ab"
  },
  {
    "id": "31087",
    "title": "Lego creator 31087 ",
    "price": 7,
    "link": "https://www.vinted.fr/items/2915438190-lego-creator-31087",
    "published": 1681745007,
    "uuid": "d6f0fe71-8ba1-4cc0-aa33-fb3948f7074b"
  },
  {
    "id": "31087",
    "title": "Lego Creator 3 en 1 Buggy des Dunes 31087",
    "price": 7,
    "link": "https://www.vinted.fr/items/4673055116-lego-creator-3-en-1-buggy-des-dunes-31087",
    "published": 1719051905,
    "uuid": "c3f5f403-68e8-4240-b228-59731b7146f8"
  },
  {
    "id": "31087",
    "title": "Lego Creator 3 in 1 (31087) très bon état",
    "price": 9.1,
    "link": "https://www.vinted.fr/items/5255866980-lego-creator-3-in-1-31087-tres-bon-etat",
    "published": 1729520863,
    "uuid": "2eac7d95-414c-484c-ba9c-1297ada07934"
  },
  {
    "id": "31087",
    "title": "Lego creator 31087",
    "price": 11.2,
    "link": "https://www.vinted.fr/items/5187926485-lego-creator-31087",
    "published": 1728483600,
    "uuid": "cf8c08f0-b35e-42cb-8749-4f10dca99061"
  },
  {
    "id": "31087",
    "title": "Lego Creator 31087",
    "price": 7,
    "link": "https://www.vinted.fr/items/5166001418-lego-creator-31087",
    "published": 1728201063,
    "uuid": "d86d8611-444a-47dd-b5c9-621a0ceaa8c9"
  },
  {
    "id": "31087",
    "title": "Lego Creator 31087",
    "price": 12.25,
    "link": "https://www.vinted.fr/items/5105594583-lego-creator-31087",
    "published": 1727268313,
    "uuid": "483d10d9-8de2-4a82-bdd1-48e9a99085c5"
  },
  {
    "id": "31087",
    "title": "Lego 31087 complet",
    "price": 5.95,
    "link": "https://www.vinted.fr/items/3670629934-lego-31087-complet",
    "published": 1698392311,
    "uuid": "83738f52-6c4e-4f52-898c-b9d53237919e"
  },
  {
    "id": "31087",
    "title": "Lego 3 véhicules ",
    "price": 4.9,
    "link": "https://www.vinted.fr/items/3281384649-lego-3-vehicules",
    "published": 1690392331,
    "uuid": "6de02fa8-4cdf-4848-a434-a16b150eb84c"
  },
  {
    "id": "31087",
    "title": "Lego creator 31087",
    "price": 5.95,
    "link": "https://www.vinted.fr/items/2415172715-lego-creator-31087",
    "published": 1668367267,
    "uuid": "76a1348c-5b90-49e7-a700-8057f54baea8"
  },
  {
    "id": "31087",
    "title": "Jouet Lego Créator le buggy des dunes numéro 31087",
    "price": 10.15,
    "link": "https://www.vinted.fr/items/5063133543-jouet-lego-creator-le-buggy-des-dunes-numero-31087",
    "published": 1726599212,
    "uuid": "31fd8136-4d29-405f-867a-6e0627ba5db4"
  },
  {
    "id": "31087",
    "title": "Lego creator 3en1 ",
    "price": 9.1,
    "link": "https://www.vinted.fr/items/3353725255-lego-creator-3en1",
    "published": 1692938513,
    "uuid": "ccc78836-59be-4c86-9393-6d07b71fe590"
  },
  {
    "id": "31087",
    "title": "Lego creator 31087 3 in 1",
    "price": 5.95,
    "link": "https://www.vinted.fr/items/5334344033-lego-creator-31087-3-in-1",
    "published": 1730817298,
    "uuid": "1f8d70c2-560e-4199-80cc-5c6804e4b4fb"
  },
  {
    "id": "31087",
    "title": "Lego 31087",
    "price": 5.95,
    "link": "https://www.vinted.fr/items/4823474416-lego-31087",
    "published": 1722264391,
    "uuid": "a9c30617-27d4-4b8d-8ccc-bceb88b121e7"
  },
  {
    "id": "31087",
    "title": "Lego 31087",
    "price": 11.2,
    "link": "https://www.vinted.fr/items/3894958693-lego-31087",
    "published": 1702929405,
    "uuid": "9639f694-4589-45cf-9146-1f084f883d83"
  },
  {
    "id": "31087",
    "title": "Lego creator",
    "price": 5.95,
    "link": "https://www.vinted.fr/items/2611290671-lego-creator",
    "published": 1674309637,
    "uuid": "be0d0529-fde4-4242-9da6-27514be144cf"
  },
  {
    "id": "31087",
    "title": "Lego 31087 buggy dune",
    "price": 3.85,
    "link": "https://www.vinted.fr/items/3517514053-lego-31087-buggy-dune",
    "published": 1727938536,
    "uuid": "3ab2019b-69d6-4bab-9d70-31e53a02459c"
  },
  {
    "id": "31087",
    "title": "Lego creator 31087 Dune buggy ",
    "price": 7.53,
    "link": "https://www.vinted.fr/items/3809919373-lego-creator-31087-dune-buggy",
    "published": 1700991723,
    "uuid": "3b7c1919-5364-45ef-9d50-37d9f84d50a1"
  },
  {
    "id": "31087",
    "title": "LEGO 31087 Creator 3 en 1 Buggy des dunes",
    "price": 10.15,
    "link": "https://www.vinted.fr/items/5318413658-lego-31087-creator-3-en-1-buggy-des-dunes",
    "published": 1730567409,
    "uuid": "7b0be782-9c2e-42d9-9db2-dad75ba8a56e"
  },
  {
    "id": "31087",
    "title": "Lot de 2 legos creato 31087 et 31043",
    "price": 11.2,
    "link": "https://www.vinted.fr/items/5215568025-lot-de-2-legos-creato-31087-et-31043",
    "published": 1728904147,
    "uuid": "da539dba-b87f-4daf-b054-3cbd1d416559"
  },
  {
    "id": "31087",
    "title": "Lego Creator 3 en 1 buggy",
    "price": 8.05,
    "link": "https://www.vinted.fr/items/4158126877-lego-creator-3-en-1-buggy",
    "published": 1709115145,
    "uuid": "4457035d-0e94-413d-b524-9ff656bad7cf"
  },
  {
    "id": "31087",
    "title": "Lego creator 3 en 1 31087",
    "price": 8.58,
    "link": "https://www.vinted.fr/items/2437261455-lego-creator-3-en-1-31087",
    "published": 1668949926,
    "uuid": "27aa2c74-910d-4c57-bb82-8ef1bea21384"
  },
  {
    "id": "31087",
    "title": "Lego creator 31087",
    "price": 7,
    "link": "https://www.vinted.fr/items/3872210590-lego-creator-31087",
    "published": 1702311473,
    "uuid": "4e71c5db-1f62-42cb-9337-a816bcd80911"
  },
  {
    "id": "31087",
    "title": "LEGO Creator 31087   Buggy des dunes",
    "price": 7,
    "link": "https://www.vinted.fr/items/3990183550-lego-creator-31087-buggy-des-dunes",
    "published": 1705502196,
    "uuid": "81bd37c4-b1bd-47ff-8bca-3fbc579afe8b"
  },
  {
    "id": "31087",
    "title": "Lego creator 3 en 1 31087",
    "price": 13.3,
    "link": "https://www.vinted.fr/items/5289536952-lego-creator-3-en-1-31087",
    "published": 1730059988,
    "uuid": "89a91837-0ced-4721-9cbe-5387ba872bf7"
  },
  {
    "id": "31087",
    "title": "Buggy des dunes playmobil ",
    "price": 5.95,
    "link": "https://www.vinted.fr/items/4268057919-buggy-des-dunes-playmobil",
    "published": 1712990339,
    "uuid": "b227c294-e645-433d-8ee4-065ab19318ea"
  },
  {
    "id": "31087",
    "title": "Lego creator 31087",
    "price": 7,
    "link": "https://www.vinted.fr/items/3433619979-lego-creator-31087",
    "published": 1693823970,
    "uuid": "33ab2cb8-ce70-44a0-b00a-dad0385dc5cc"
  },
  {
    "id": "31087",
    "title": "Lego creator 3 en 1 31087",
    "price": 9.1,
    "link": "https://www.vinted.fr/items/4267428663-lego-creator-3-en-1-31087",
    "published": 1711294005,
    "uuid": "4948219f-689e-464d-bb61-4c02b4f9518a"
  },
  {
    "id": "31087",
    "title": "Lego 31087",
    "price": 8.05,
    "link": "https://www.vinted.fr/items/5181329442-lego-31087",
    "published": 1728387711,
    "uuid": "5a98b8ec-3bad-4594-84c3-2b84eafe4b3d"
  },
  {
    "id": "31087",
    "title": "Lego creator 3 en 1",
    "price": 9.1,
    "link": "https://www.vinted.fr/items/3816886455-lego-creator-3-en-1",
    "published": 1701093993,
    "uuid": "7fe95f8b-c704-4204-9873-96655dced51e"
  },
  {
    "id": "31087",
    "title": "Lego creator 31087",
    "price": 11.2,
    "link": "https://www.vinted.fr/items/4893822657-lego-creator-31087",
    "published": 1723808938,
    "uuid": "825a762b-0604-46e6-bef8-67cebcce4072"
  },
  {
    "id": "31087",
    "title": "LEGO Le Buggy des Dunes 31087",
    "price": 11.2,
    "link": "https://www.vinted.fr/items/3668706538-lego-le-buggy-des-dunes-31087",
    "published": 1698335149,
    "uuid": "bbb2c678-6af0-45ef-828e-d76fa8df54e3"
  },
  {
    "id": "31087",
    "title": "Lego creator 31087",
    "price": 9.1,
    "link": "https://www.vinted.fr/items/3697559486-lego-creator-31087",
    "published": 1698865461,
    "uuid": "a562652c-7b70-4322-bc80-728daf021c26"
  },
  {
    "id": "31087",
    "title": "Lego creator 31087",
    "price": 9.1,
    "link": "https://www.vinted.fr/items/3600899195-lego-creator-31087",
    "published": 1697179825,
    "uuid": "e01b72f6-62f6-452b-8588-ca81cb2be474"
  },
  {
    "id": "31087",
    "title": "Lego 3 en 1 31087",
    "price": 5.95,
    "link": "https://www.vinted.fr/items/4498489626-lego-3-en-1-31087",
    "published": 1715613164,
    "uuid": "8ca9cbc5-0670-449c-9ee4-abe96e171fd5"
  },
  {
    "id": "31087",
    "title": "Lego creator 31087. 3 en 1.  Le buggy des dunes",
    "price": 8.05,
    "link": "https://www.vinted.fr/items/4845749527-lego-creator-31087-3-en-1-le-buggy-des-dunes",
    "published": 1722777301,
    "uuid": "94e6a71e-e452-4d6c-a4c3-f98149468f3e"
  },
  {
    "id": "31087",
    "title": "Lego créator 31087 Le buggy des dunes ",
    "price": 7,
    "link": "https://www.vinted.fr/items/4117778601-lego-creator-31087-le-buggy-des-dunes",
    "published": 1708277980,
    "uuid": "d2811ee1-41d4-4b8e-87cf-c627bd2a3948"
  },
  {
    "id": "31087",
    "title": "Lego set 31087, 30352, gelpennen",
    "price": 16.45,
    "link": "https://www.vinted.fr/items/4721661338-lego-set-31087-30352-gelpennen",
    "published": 1720085865,
    "uuid": "0abe4f66-fa65-414d-9e65-eb976c962e01"
  },
  {
    "id": "31087",
    "title": "Lego 31087",
    "price": 5.95,
    "link": "https://www.vinted.fr/items/4839433958-lego-31087",
    "published": 1722624280,
    "uuid": "80ace641-8425-49ac-bb27-144eafad63ba"
  },
  {
    "id": "31087",
    "title": "Lego creator 31087",
    "price": 7,
    "link": "https://www.vinted.fr/items/1638109603-lego-creator-31087",
    "published": 1645034785,
    "uuid": "caba43bf-3a35-4348-94c9-7b7d411ffc15"
  },
  {
    "id": "31087",
    "title": "Lego Buggy",
    "price": 11.2,
    "link": "https://www.vinted.fr/items/4964805607-lego-buggy",
    "published": 1725098566,
    "uuid": "c1d3e141-4495-497c-9645-305c7d1e760a"
  },
  {
    "id": "31087",
    "title": "LEGO 31087 Buggy, avion et tout terrain ",
    "price": 11.2,
    "link": "https://www.vinted.fr/items/3812214658-lego-31087-buggy-avion-et-tout-terrain",
    "published": 1701010210,
    "uuid": "e7f4eecf-e756-490d-8e9a-93c2944c6dff"
  },
  {
    "id": "31087",
    "title": "Lego creator 31087",
    "price": 9.1,
    "link": "https://www.vinted.fr/items/5343339562-lego-creator-31087",
    "published": 1730986819,
    "uuid": "0c58aa43-078a-4c65-8985-754ccc9ebd35"
  },
  {
    "id": "31087",
    "title": "Lego creator",
    "price": 11.2,
    "link": "https://www.vinted.fr/items/5257391360-lego-creator",
    "published": 1729534638,
    "uuid": "bd21a91e-1c6d-4cc2-a20a-0d19d5b946c2"
  },
  {
    "id": "31087",
    "title": "Lego Creator 31087 : Buggy des Dunes",
    "price": 5.95,
    "link": "https://www.vinted.fr/items/5255522657-lego-creator-31087-buggy-des-dunes",
    "published": 1729517992,
    "uuid": "cb92429e-05c7-4b46-a360-ebef7b93a750"
  },
  {
    "id": "31087",
    "title": "Lego creator 31087 buggy avion quad",
    "price": 9.1,
    "link": "https://www.vinted.fr/items/5142380294-lego-creator-31087-buggy-avion-quad",
    "published": 1727802053,
    "uuid": "f38995b4-fed7-43b3-9b0d-5496aa1a8af4"
  },
  {
    "id": "31087",
    "title": "Lego creator  nr 31087",
    "price": 11.2,
    "link": "https://www.vinted.fr/items/4425487104-lego-creator-nr-31087",
    "published": 1714241351,
    "uuid": "32fb92b8-6d26-4082-869b-61d9666643cb"
  },
  {
    "id": "31087",
    "title": "Lego creator nr. 31087",
    "price": 4.9,
    "link": "https://www.vinted.fr/items/5349349717-lego-creator-nr-31087",
    "published": 1731090474,
    "uuid": "ac76ede5-d099-4c88-93cf-d8bd097c9f7f"
  },
  {
    "id": "31087",
    "title": "LEGO® Creator 3 en 1 31087 Le buggy des dunes",
    "price": 21.7,
    "link": "https://www.vinted.fr/items/5302117151-legor-creator-3-en-1-31087-le-buggy-des-dunes",
    "published": 1730289902,
    "uuid": "4b68e194-5adf-444d-be1a-dd18b2070958"
  },
  {
    "id": "31087",
    "title": "Lego creator 31087",
    "price": 8.05,
    "link": "https://www.vinted.fr/items/3451438175-lego-creator-31087",
    "published": 1694254964,
    "uuid": "9ab9aa7f-560a-4905-80e9-f1a147a9e9fd"
  },
  {
    "id": "31087",
    "title": "Lego 31087 creator 3 in 1",
    "price": 9.1,
    "link": "https://www.vinted.fr/items/5132556485-lego-31087-creator-3-in-1",
    "published": 1727643682,
    "uuid": "68d7cf77-9ffb-4870-92fd-87cf9c6fc9a4"
  },
  {
    "id": "31087",
    "title": "Lego creator",
    "price": 4.9,
    "link": "https://www.vinted.fr/items/4634650458-lego-creator",
    "published": 1718216403,
    "uuid": "e8d3ee4c-27c7-44fe-a81b-40c075ef3d85"
  },
  {
    "id": "31087",
    "title": "Lego Creator 3en1  N. 31087",
    "price": 21.7,
    "link": "https://www.vinted.fr/items/5029714255-lego-creator-3en1-n-31087",
    "published": 1726139433,
    "uuid": "f5b4245b-c429-4400-a64d-a87176cde0aa"
  },
  {
    "id": "31087",
    "title": "Nieuwe lego creator",
    "price": 11.2,
    "link": "https://www.vinted.fr/items/5202431990-nieuwe-lego-creator",
    "published": 1728734265,
    "uuid": "63a90b5f-5a54-4211-baa3-cdd2fa40dc39"
  },
  {
    "id": "31087",
    "title": "Lego creator 31087",
    "price": 9.1,
    "link": "https://www.vinted.fr/items/2613496590-lego-creator-31087",
    "published": 1674380396,
    "uuid": "0940e364-24e4-4b75-af72-9cf239f3c541"
  },
  {
    "id": "31087",
    "title": "Lego creator 31087 anni 6+",
    "price": 7,
    "link": "https://www.vinted.fr/items/4669074241-lego-creator-31087-anni-6",
    "published": 1718956431,
    "uuid": "0a74d430-1c1e-4d20-8cf6-f222e500ad1e"
  },
  {
    "id": "31087",
    "title": "Lego Creator 3in1 31087",
    "price": 11.2,
    "link": "https://www.vinted.fr/items/5005716773-lego-creator-3in1-31087",
    "published": 1725797678,
    "uuid": "23469920-481e-4d79-9c4f-9de2d0787823"
  },
  {
    "id": "31087",
    "title": "Lego creator 31087",
    "price": 11.2,
    "link": "https://www.vinted.fr/items/3036947090-lego-creator-31087",
    "published": 1684478924,
    "uuid": "2798cb43-6196-4c09-968a-05e6e94bea87"
  },
  {
    "id": "31087",
    "title": "Lego creator 31087",
    "price": 5.95,
    "link": "https://www.vinted.fr/items/4466485196-lego-creator-31087",
    "published": 1715002748,
    "uuid": "ec3eb36f-355f-4619-b6f8-5d302a8daf49"
  },
  {
    "id": "31087",
    "title": "Lego creator 3 en 1",
    "price": 8.05,
    "link": "https://www.vinted.fr/items/3711396673-lego-creator-3-en-1",
    "published": 1699117044,
    "uuid": "4ab46375-8348-4581-9755-3f58f843acbf"
  },
  {
    "id": "31087",
    "title": "Lego 31087",
    "price": 2.8,
    "link": "https://www.vinted.fr/items/2608235674-lego-31087",
    "published": 1674221946,
    "uuid": "ac777eeb-5db0-4b93-8dba-90c00d930a12"
  },
  {
    "id": "31087",
    "title": "lego creator 31087",
    "price": 11.2,
    "link": "https://www.vinted.fr/items/4927904337-lego-creator-31087",
    "published": 1724428552,
    "uuid": "343ac196-7893-461c-a9e2-a3b357c52eb2"
  },
  {
    "id": "31087",
    "title": "Notice livret Lego Creator 3en1 31087 quad",
    "price": 2.8,
    "link": "https://www.vinted.fr/items/3526815829-notice-livret-lego-creator-3en1-31087-quad",
    "published": 1695736663,
    "uuid": "6f760adf-d8df-415e-9674-f320da700446"
  },
  {
    "id": "31087",
    "title": "LEGO Creator 3 in 1, 31087 Dune Buggy, auto",
    "price": 9.1,
    "link": "https://www.vinted.fr/items/5187519022-lego-creator-3-in-1-31087-dune-buggy-auto",
    "published": 1728480238,
    "uuid": "f4294153-0e03-4ef2-bdd7-80386e4b70e1"
  },
  {
    "id": "31087",
    "title": "Notice livret Lego Creator 3en1 31087 Véhicule ",
    "price": 2.8,
    "link": "https://www.vinted.fr/items/3526823592-notice-livret-lego-creator-3en1-31087-vehicule",
    "published": 1695736753,
    "uuid": "fd550bfd-38d3-44f9-909d-43afc417173f"
  },
  {
    "id": "31087",
    "title": "Lego 31087",
    "price": 5.95,
    "link": "https://www.vinted.fr/items/1456276664-lego-31087",
    "published": 1637427502,
    "uuid": "70a4d663-f34e-4524-a28d-f16b89206ebd"
  },
  {
    "id": "31087",
    "title": "Lego 31087 - Buggy des dunes",
    "price": 7,
    "link": "https://www.vinted.fr/items/5187348502-lego-31087-buggy-des-dunes",
    "published": 1728478848,
    "uuid": "6e241d28-f1b3-48d7-ac11-a4e8d24ff083"
  },
  {
    "id": "31087",
    "title": "Lego Creator 31087",
    "price": 9.1,
    "link": "https://www.vinted.fr/items/2963057265-lego-creator-31087",
    "published": 1682862683,
    "uuid": "035be0e3-347a-49d6-9ed1-13ad7d5686e2"
  },
  {
    "id": "31087",
    "title": "Lego creator 31087",
    "price": 9.1,
    "link": "https://www.vinted.fr/items/2415868130-lego-creator-31087",
    "published": 1668381274,
    "uuid": "55c5c9c4-36c3-4737-bf8b-567ce8111500"
  },
  {
    "id": "31087",
    "title": "Lego Creator 31087",
    "price": 11.2,
    "link": "https://www.vinted.fr/items/4800801464-lego-creator-31087",
    "published": 1721755229,
    "uuid": "8d261613-dce0-4af8-bc31-13af34733cda"
  },
  {
    "id": "31087",
    "title": "Lego Creator 31087",
    "price": 11.2,
    "link": "https://www.vinted.fr/items/4986838942-lego-creator-31087",
    "published": 1725460575,
    "uuid": "d6c60201-63e0-4c2b-8e88-4164fc11b8ad"
  },
  {
    "id": "31087",
    "title": "Lego Creator ref 31087",
    "price": 14.35,
    "link": "https://www.vinted.fr/items/3044056515-lego-creator-ref-31087",
    "published": 1684656561,
    "uuid": "88349aaf-ed34-4bda-9439-c74bb1f3cf5e"
  },
  {
    "id": "31087",
    "title": "Lego Creator 31087",
    "price": 11.2,
    "link": "https://www.vinted.fr/items/5251784282-lego-creator-31087",
    "published": 1729448582,
    "uuid": "04792fef-2972-46e1-aa55-d9c8ad2d9b48"
  },
  {
    "id": "31087",
    "title": "Lego creator 3en1 31087",
    "price": 11.2,
    "link": "https://www.vinted.fr/items/4561555483-lego-creator-3en1-31087",
    "published": 1716814811,
    "uuid": "4aca6be6-5c8e-4d22-b140-c1f3486aa04f"
  },
  {
    "id": "31087",
    "title": "Lego creator 31087",
    "price": 5.95,
    "link": "https://www.vinted.fr/items/3298116592-lego-creator-31087",
    "published": 1690814886,
    "uuid": "7ca9a657-1d23-447e-926c-1524cdd93800"
  },
  {
    "id": "31087",
    "title": "Lego 31087",
    "price": 7,
    "link": "https://www.vinted.fr/items/3341956313-lego-31087",
    "published": 1691839858,
    "uuid": "83ae6367-c9d0-48e2-82d3-4f822c8d57d3"
  },
  {
    "id": "31087",
    "title": "Lego Creator-Set 31087",
    "price": 15.19,
    "link": "https://www.vinted.fr/items/1465674508-lego-creator-set-31087",
    "published": 1637823309,
    "uuid": "ea30d235-a7e9-43e2-bc0b-5cf5acb77854"
  },
  {
    "id": "31087",
    "title": "Lego creator 3 en 1",
    "price": 11.2,
    "link": "https://www.vinted.fr/items/4959263665-lego-creator-3-en-1",
    "published": 1724965093,
    "uuid": "c94427ac-6366-4b7d-bab6-bf92cd242079"
  },
  {
    "id": "31087",
    "title": "lego creator 3 en 1 31087",
    "price": 11.2,
    "link": "https://www.vinted.fr/items/3459902229-lego-creator-3-en-1-31087",
    "published": 1694433319,
    "uuid": "1ef504f4-a114-4bd4-83ef-47d7d152c317"
  },
  {
    "id": "31087",
    "title": "Lego creator 31087",
    "price": 8.05,
    "link": "https://www.vinted.fr/items/4535636501-lego-creator-31087",
    "published": 1716302287,
    "uuid": "0e02ce57-48db-48fc-ab9e-0888e5163a72"
  },
  {
    "id": "31087",
    "title": "Lego creator 31087",
    "price": 11.2,
    "link": "https://www.vinted.fr/items/4063588665-lego-creator-31087",
    "published": 1707075303,
    "uuid": "0ecead3e-9591-4715-8d92-d89725d2a958"
  },
  {
    "id": "31087",
    "title": "Lego Creator 31087",
    "price": 9.1,
    "link": "https://www.vinted.fr/items/5297538766-lego-creator-31087",
    "published": 1730275095,
    "uuid": "c4503355-71d8-4a63-a993-0603ed1bc771"
  },
  {
    "id": "31087",
    "title": "Set lego creator n. 31087",
    "price": 11.2,
    "link": "https://www.vinted.fr/items/3892405997-set-lego-creator-n-31087",
    "published": 1702847143,
    "uuid": "274ebd89-4ffd-4f83-a5ce-d797463eb0cc"
  },
  {
    "id": "31087",
    "title": "Lego Creator 31087 - 6+",
    "price": 5.95,
    "link": "https://www.vinted.fr/items/3305456757-lego-creator-31087-6",
    "published": 1690982163,
    "uuid": "31f80ade-ea6d-4d60-b70d-f598e05a20a5"
  },
  {
    "id": "31087",
    "title": "Lego creator ",
    "price": 12.78,
    "link": "https://www.vinted.fr/items/3634291176-lego-creator",
    "published": 1697744342,
    "uuid": "8108d05a-e594-4422-b488-7a7f5d8e09d7"
  },
  {
    "id": "31087",
    "title": "LEGO Creator 31087",
    "price": 10.15,
    "link": "https://www.vinted.fr/items/4500428434-lego-creator-31087",
    "published": 1715636346,
    "uuid": "796dcb56-5705-47b6-8d38-2be02c6c6b01"
  },
  {
    "id": "31087",
    "title": "Lego creator 3 en 1  31087",
    "price": 11.2,
    "link": "https://www.vinted.fr/items/4791625607-lego-creator-3-en-1-31087",
    "published": 1721576849,
    "uuid": "ab627458-8f36-4946-a519-a24ff2273527"
  },
  {
    "id": "31087",
    "title": "Black Sabbath - Paranoid - lp vinyl (1990)",
    "price": 26.95,
    "link": "https://www.vinted.fr/items/5342365958-black-sabbath-paranoid-lp-vinyl-1990",
    "published": 1730976498,
    "uuid": "58bbb89b-070f-4aad-bcfb-fde6b5a38990"
  },
  {
    "id": "31087",
    "title": "Lego creator 31087",
    "price": 11.2,
    "link": "https://www.vinted.fr/items/2228480304-lego-creator-31087",
    "published": 1663853980,
    "uuid": "b3ac4221-9bd1-4bb3-a95d-9017fca35763"
  },
  {
    "id": "31087",
    "title": "Lego creator 31087",
    "price": 5.95,
    "link": "https://www.vinted.fr/items/3800053342-lego-creator-31087",
    "published": 1700758339,
    "uuid": "01aceace-fa78-46db-8468-9e94f8954d9d"
  },
  {
    "id": "31087",
    "title": "Lego creator 31087",
    "price": 8.05,
    "link": "https://www.vinted.fr/items/4926893941-lego-creator-31087",
    "published": 1724842556,
    "uuid": "877a573d-bbf5-4866-898d-ee9349013e7c"
  },
  {
    "id": "31087",
    "title": "Lego créator 31087",
    "price": 12.25,
    "link": "https://www.vinted.fr/items/5169797783-lego-creator-31087",
    "published": 1728223742,
    "uuid": "b96093b9-5985-489d-a680-164af27266eb"
  },
  {
    "id": "31087",
    "title": "Lego 3 in 1, Nummer 31087",
    "price": 7,
    "link": "https://www.vinted.fr/items/5162640906-lego-3-in-1-nummer-31087",
    "published": 1728136331,
    "uuid": "e2e2e975-92aa-46ec-855c-1055b4aff80e"
  },
  {
    "id": "31087",
    "title": "Lego Creator set 31087, 3 in 1 set Buggy, vliegtuig of Quad nieuw in doos",
    "price": 13.83,
    "link": "https://www.vinted.fr/items/5341934533-lego-creator-set-31087-3-in-1-set-buggy-vliegtuig-of-quad-nieuw-in-doos",
    "published": 1730971611,
    "uuid": "c65f4d48-d488-4099-84f6-95be025a7150"
  },
  {
    "id": "31087",
    "title": "Lego Creator 31087",
    "price": 7,
    "link": "https://www.vinted.fr/items/5154496494-lego-creator-31087",
    "published": 1727989718,
    "uuid": "2de0d697-3526-4de9-b82c-bb22aad988b7"
  },
  {
    "id": "31087",
    "title": "Lego créatif 2 voitures",
    "price": 13.3,
    "link": "https://www.vinted.fr/items/5286984972-lego-creatif-2-voitures",
    "published": 1730040260,
    "uuid": "670bbc5e-45cd-47a1-974b-71a4fd4fd100"
  },
  {
    "id": "31087",
    "title": "Lego 31087 dune buggy",
    "price": 9.1,
    "link": "https://www.vinted.fr/items/4509347284-lego-31087-dune-buggy",
    "published": 1715805248,
    "uuid": "eeadad54-5ce0-4da2-99a2-6c81e6e9f9e3"
  },
  {
    "id": "31087",
    "title": "Lego creator 31087",
    "price": 13.3,
    "link": "https://www.vinted.fr/items/5169152443-lego-creator-31087",
    "published": 1728220589,
    "uuid": "e21b577b-aaf5-4dca-806b-901643d2a03a"
  },
  {
    "id": "31087",
    "title": "Lego 31087",
    "price": 9.1,
    "link": "https://www.vinted.fr/items/5126756112-lego-31087",
    "published": 1727607054,
    "uuid": "71879906-ccaf-41b1-aaca-b6dec39ce120"
  },
  {
    "id": "31087",
    "title": "LEGO Creator 3 en 1-31087 : Le buggy des dunes",
    "price": 18.55,
    "link": "https://www.vinted.fr/items/4220520932-lego-creator-3-en-1-31087-le-buggy-des-dunes",
    "published": 1710364923,
    "uuid": "49d8112f-fb07-447b-8fe5-e5858f6ee34a"
  },
  {
    "id": "31087",
    "title": "Voiture Lego creator ",
    "price": 9.1,
    "link": "https://www.vinted.fr/items/3915883689-voiture-lego-creator",
    "published": 1703783570,
    "uuid": "f98e34eb-fad2-4d49-bcda-e4c93304ffd4"
  },
  {
    "id": "31087",
    "title": "Lego 3 en1 31087",
    "price": 10.15,
    "link": "https://www.vinted.fr/items/3849638259-lego-3-en1-31087",
    "published": 1701802893,
    "uuid": "eebef3a3-75f4-4245-93bd-37fa57aa8947"
  },
  {
    "id": "31087",
    "title": "Lego creator 31087",
    "price": 7,
    "link": "https://www.vinted.fr/items/1329993037-lego-creator-31087",
    "published": 1632482702,
    "uuid": "96f29a26-6541-496b-8853-54c8d672ad7e"
  },
  {
    "id": "31087",
    "title": "Lego creator 31087",
    "price": 11.2,
    "link": "https://www.vinted.fr/items/4810548888-lego-creator-31087",
    "published": 1721986032,
    "uuid": "42a62901-20c6-46a4-b986-e2eb8cf0ca74"
  },
  {
    "id": "31087",
    "title": "Lego 31087",
    "price": 11.2,
    "link": "https://www.vinted.fr/items/3688280677-lego-31087",
    "published": 1698687067,
    "uuid": "d228fb68-2a06-4b5b-8331-630379f9f9c4"
  },
  {
    "id": "31087",
    "title": "Lego Creator 3 en 1",
    "price": 8.58,
    "link": "https://www.vinted.fr/items/5101795287-lego-creator-3-en-1",
    "published": 1727197134,
    "uuid": "f8910af0-c4af-467a-8582-16515d6e0218"
  },
  {
    "id": "31087",
    "title": "Lego 31087",
    "price": 12.78,
    "link": "https://www.vinted.fr/items/4426932134-lego-31087",
    "published": 1714294826,
    "uuid": "f8ccd31c-28e9-4f3c-acb3-8c487a6729ed"
  },
  {
    "id": "31087",
    "title": "Lego Creator 31087 ( 3 in 1 ) Dune Buggy",
    "price": 8.58,
    "link": "https://www.vinted.fr/items/5245966137-lego-creator-31087-3-in-1-dune-buggy",
    "published": 1729411854,
    "uuid": "2dd637ef-e874-4041-b7cf-6fecd56716ea"
  },
  {
    "id": "31087",
    "title": "Lego creator 31087",
    "price": 12.25,
    "link": "https://www.vinted.fr/items/2385451150-lego-creator-31087",
    "published": 1667668909,
    "uuid": "ac142e75-463b-4e2d-957c-3fc13cb0b726"
  },
  {
    "id": "31087",
    "title": "Lego 31087",
    "price": 8.58,
    "link": "https://www.vinted.fr/items/4589106028-lego-31087",
    "published": 1717339162,
    "uuid": "9cf0ad70-1576-43ac-842d-4086008af821"
  },
  {
    "id": "31087",
    "title": "Lego Creator 31087",
    "price": 9.1,
    "link": "https://www.vinted.fr/items/5161622726-lego-creator-31087",
    "published": 1728129036,
    "uuid": "a21531fd-1531-4bef-943b-7744afa3929d"
  },
  {
    "id": "31087",
    "title": "Lego creator 3in1 31087",
    "price": 8.58,
    "link": "https://www.vinted.fr/items/3448121650-lego-creator-3in1-31087",
    "published": 1694165761,
    "uuid": "67d15ae9-eda1-48fc-8ce8-76006969c7cd"
  },
  {
    "id": "31087",
    "title": "Lego 31087 Dune buggy",
    "price": 8.58,
    "link": "https://www.vinted.fr/items/4913701179-lego-31087-dune-buggy",
    "published": 1724168842,
    "uuid": "f39c8e2b-2a64-4373-bc15-3490c26e576b"
  },
  {
    "id": "31087",
    "title": "Lego Creator 31087",
    "price": 8.05,
    "link": "https://www.vinted.fr/items/2351107379-lego-creator-31087",
    "published": 1666774994,
    "uuid": "05ec160a-b483-4aaf-9874-b98bd84a67da"
  },
  {
    "id": "31087",
    "title": "Lego Creator 3 in 1 Dune Buggy 31087",
    "price": 11.2,
    "link": "https://www.vinted.fr/items/5188894242-lego-creator-3-in-1-dune-buggy-31087",
    "published": 1728491716,
    "uuid": "fb60be5a-ef8b-462f-b77f-da14a4dd6d4b"
  },
  {
    "id": "31087",
    "title": "Lego 3 en 1 le buggy des dunes 31087",
    "price": 9.1,
    "link": "https://www.vinted.fr/items/4041039523-lego-3-en-1-le-buggy-des-dunes-31087",
    "published": 1706612584,
    "uuid": "9828dfc5-920a-4755-8353-a5a7a333d5dd"
  },
  {
    "id": "31087",
    "title": "Lego creator 31087 dune buggie NIEUW",
    "price": 16.45,
    "link": "https://www.vinted.fr/items/3776076613-lego-creator-31087-dune-buggie-nieuw",
    "published": 1700318668,
    "uuid": "f0252182-98f4-4704-aa45-51e44ce3ed37"
  },
  {
    "id": "31087",
    "title": "Lego dune buggy 31087",
    "price": 8.58,
    "link": "https://www.vinted.fr/items/5157042762-lego-dune-buggy-31087",
    "published": 1728048663,
    "uuid": "c7dcb99b-f570-4cff-8e70-4b8addfe8c80"
  },
  {
    "id": "31087",
    "title": "Lego Creator 3 in 1 Dune Buggy 31087",
    "price": 7.53,
    "link": "https://www.vinted.fr/items/3375277377-lego-creator-3-in-1-dune-buggy-31087",
    "published": 1692629961,
    "uuid": "8c5ee92c-9318-41a8-b5da-5492c258f26b"
  },
  {
    "id": "31087",
    "title": "Lego Creator 3in1 ",
    "price": 8.58,
    "link": "https://www.vinted.fr/items/3765296698-lego-creator-3in1",
    "published": 1700078914,
    "uuid": "dd311c9b-c4f0-4e75-a6c6-6f5767b42cfe"
  },
  {
    "id": "31087",
    "title": "Lego creator 31087",
    "price": 10.15,
    "link": "https://www.vinted.fr/items/3284515079-lego-creator-31087",
    "published": 1690476195,
    "uuid": "d1a0bd46-80cd-4af1-906d-e10729e9b19e"
  },
  {
    "id": "31087",
    "title": "Lego Creator 31087 3 en 1",
    "price": 12.25,
    "link": "https://www.vinted.fr/items/3893748043-lego-creator-31087-3-en-1",
    "published": 1702906337,
    "uuid": "84bc5178-b1e0-41e6-bd34-c6a2f7a59124"
  },
  {
    "id": "31087",
    "title": "Twee lego auto’s",
    "price": 11.2,
    "link": "https://www.vinted.fr/items/5024769054-twee-lego-autos",
    "published": 1729974016,
    "uuid": "7a2bcd72-4095-4542-9246-4504a5fd41c2"
  },
  {
    "id": "31087",
    "title": "Lego Creator - 31087",
    "price": 11.2,
    "link": "https://www.vinted.fr/items/5212971577-lego-creator-31087",
    "published": 1728845027,
    "uuid": "d59ea42b-5023-47fa-8f55-1c713250605f"
  },
  {
    "id": "31087",
    "title": "Lego creator 31087 le buggy",
    "price": 5.95,
    "link": "https://www.vinted.fr/items/770067403-lego-creator-31087-le-buggy",
    "published": 1606590347,
    "uuid": "e31948d0-053d-42ed-b37b-d334c1b964ac"
  },
  {
    "id": "31087",
    "title": "LEGO set 31087",
    "price": 7.53,
    "link": "https://www.vinted.fr/items/4904902638-lego-set-31087",
    "published": 1724005333,
    "uuid": "8c62fe5a-1dac-488a-b85c-b7bbf6355329"
  },
  {
    "id": "31087",
    "title": "Lego creator dune buggy 31087 3 in 1",
    "price": 5.95,
    "link": "https://www.vinted.fr/items/4987010960-lego-creator-dune-buggy-31087-3-in-1",
    "published": 1725462193,
    "uuid": "940f98e9-72d6-4124-8d24-fd66397ea87e"
  },
  {
    "id": "31087",
    "title": "Lego creator 31087",
    "price": 16.45,
    "link": "https://www.vinted.fr/items/4645157172-lego-creator-31087",
    "published": 1718458423,
    "uuid": "9958d8e4-b821-4f5e-a733-832c2f7270b6"
  },
  {
    "id": "31087",
    "title": "Lego 31087",
    "price": 13.3,
    "link": "https://www.vinted.fr/items/5230629797-lego-31087",
    "published": 1729151517,
    "uuid": "0803a895-f5fe-47fa-87b5-b62d95af7d48"
  },
  {
    "id": "31087",
    "title": "Lego Creator 31087",
    "price": 11.2,
    "link": "https://www.vinted.fr/items/4598851636-lego-creator-31087",
    "published": 1717517058,
    "uuid": "088dff2f-5dc5-49e6-99db-9713e3aab616"
  },
  {
    "id": "31087",
    "title": "Lego creator",
    "price": 16.45,
    "link": "https://www.vinted.fr/items/4898021328-lego-creator",
    "published": 1723898903,
    "uuid": "32172ded-5eb9-4f31-b2cf-3e7d019ca50b"
  },
  {
    "id": "31087",
    "title": "Lego 31087- le buggy des dunes",
    "price": 11.2,
    "link": "https://www.vinted.fr/items/1471433851-lego-31087-le-buggy-des-dunes",
    "published": 1638096248,
    "uuid": "9607484f-689c-42dc-a2cc-839d6c89ff36"
  },
  {
    "id": "31087",
    "title": "Lego Creator 31087",
    "price": 11.2,
    "link": "https://www.vinted.fr/items/2501749549-lego-creator-31087",
    "published": 1670755569,
    "uuid": "e1a3dc06-2b09-4e7c-9528-a7b85f3ba13b"
  },
  {
    "id": "31087",
    "title": "Lego Creator 3in1",
    "price": 5.95,
    "link": "https://www.vinted.fr/items/2908220309-lego-creator-3in1",
    "published": 1681628920,
    "uuid": "d69ac537-047b-4ac2-84ff-b7cc0d98f47a"
  },
  {
    "id": "31087",
    "title": "Lego 30187 buggy creator ",
    "price": 7,
    "link": "https://www.vinted.fr/items/3777954241-lego-30187-buggy-creator",
    "published": 1700341147,
    "uuid": "f0160e41-73da-4b95-b1e1-6c4843a5429e"
  },
  {
    "id": "31087",
    "title": "Lego 3en 1 31087",
    "price": 16.45,
    "link": "https://www.vinted.fr/items/3686207842-lego-3en-1-31087",
    "published": 1698664900,
    "uuid": "40b5ca3e-2b28-46ec-9dcb-2eebfdc4fe1d"
  },
  {
    "id": "31087",
    "title": "Lego Creator Buggy 31087",
    "price": 16.45,
    "link": "https://www.vinted.fr/items/3792759926-lego-creator-buggy-31087",
    "published": 1700599935,
    "uuid": "494e6109-7692-494a-8b4e-1435c47765c3"
  },
  {
    "id": "31087",
    "title": "Lego 31087 creator 3 in 1",
    "price": 8.58,
    "link": "https://www.vinted.fr/items/4765601393-lego-31087-creator-3-in-1",
    "published": 1720982266,
    "uuid": "98852f85-2ef5-40a7-88be-24f9eeb750b5"
  },
  {
    "id": "31087",
    "title": "Lego creator 31087",
    "price": 10.15,
    "link": "https://www.vinted.fr/items/4248668158-lego-creator-31087",
    "published": 1710939077,
    "uuid": "94538372-6c9c-4c51-a249-a7abd8221ddc"
  },
  {
    "id": "31087",
    "title": "Lego Creator 31087 Dune Buggy 3 in 1 compleet",
    "price": 11.2,
    "link": "https://www.vinted.fr/items/5268662935-lego-creator-31087-dune-buggy-3-in-1-compleet",
    "published": 1729721323,
    "uuid": "0d3b8445-3550-41ad-beb0-8ff71eafef7f"
  },
  {
    "id": "31087",
    "title": "Lego 31087",
    "price": 11.2,
    "link": "https://www.vinted.fr/items/5252467548-lego-31087",
    "published": 1729455339,
    "uuid": "f3ca0ddf-6673-49ad-83a1-cc92d3245382"
  },
  {
    "id": "31087",
    "title": "Lego Creator 3en1",
    "price": 21.7,
    "link": "https://www.vinted.fr/items/5007863087-lego-creator-3en1",
    "published": 1725809676,
    "uuid": "3b7d3838-8ce0-4304-814a-99564f106d58"
  },
  {
    "id": "31087",
    "title": "Notice livret Lego Creator  31087",
    "price": 2.8,
    "link": "https://www.vinted.fr/items/3530956113-notice-livret-lego-creator-31087",
    "published": 1695820826,
    "uuid": "8b3da1f4-25af-4107-b169-c1d92862ba34"
  },
  {
    "id": "31087",
    "title": "Lego Creator 3 in 1 31087.",
    "price": 11.2,
    "link": "https://www.vinted.fr/items/4944778988-lego-creator-3-in-1-31087",
    "published": 1724704696,
    "uuid": "8f68bc9e-8ba9-41e9-b6fa-a97bb808c4bd"
  },
  {
    "id": "31087",
    "title": "Lego creator 3 in 1",
    "price": 9.1,
    "link": "https://www.vinted.fr/items/4813070132-lego-creator-3-in-1",
    "published": 1722023212,
    "uuid": "c9832eee-ab8c-4cda-956c-f1d8fcbf40d1"
  },
  {
    "id": "31087",
    "title": "Lego Creator 31087 Le buggy des dunes, neuf jamais ouvert",
    "price": 16.45,
    "link": "https://www.vinted.fr/items/3471735061-lego-creator-31087-le-buggy-des-dunes-neuf-jamais-ouvert",
    "published": 1694691173,
    "uuid": "7b57d81f-44df-4e32-bd56-06510c156070"
  },
  {
    "id": "31087",
    "title": "Lego 31087",
    "price": 21.7,
    "link": "https://www.vinted.fr/items/4019682418-lego-31087",
    "published": 1706126938,
    "uuid": "282767f1-bda6-4724-b5a5-5bd4c597b903"
  },
  {
    "id": "31087",
    "title": "Lego Creator Dune Buggy 31087",
    "price": 16.45,
    "link": "https://www.vinted.fr/items/5180863646-lego-creator-dune-buggy-31087",
    "published": 1728383191,
    "uuid": "4a3d0506-43b4-4105-91e9-db9ce26b8497"
  },
  {
    "id": "31087",
    "title": "Lego Creator | Creator 3-in-1 | Dune buggy 31087",
    "price": 5.95,
    "link": "https://www.vinted.fr/items/5030200907-lego-creator-creator-3-in-1-dune-buggy-31087",
    "published": 1726143977,
    "uuid": "140c7b52-7c1a-4f19-b5fa-484439aaf016"
  },
  {
    "id": "31087",
    "title": "Lego creator 31087",
    "price": 16.45,
    "link": "https://www.vinted.fr/items/5276180470-lego-creator-31087",
    "published": 1729868542,
    "uuid": "86d3f0e5-d121-4119-9b32-795cdf75045b"
  },
  {
    "id": "31087",
    "title": "Lego Creator 3in1 Cod. 31087 fuoristrada ",
    "price": 5.43,
    "link": "https://www.vinted.fr/items/3873901921-lego-creator-3in1-cod-31087-fuoristrada",
    "published": 1702354652,
    "uuid": "691e1538-91ed-4afd-8701-8e063633547c"
  },
  {
    "id": "31087",
    "title": "Lego creator 3en1 31087",
    "price": 21.7,
    "link": "https://www.vinted.fr/items/4373716760-lego-creator-3en1-31087",
    "published": 1713283344,
    "uuid": "0ad88845-51c4-4b3a-b872-3e5115cbb684"
  },
  {
    "id": "31087",
    "title": "Lego creator ref 31087",
    "price": 18.55,
    "link": "https://www.vinted.fr/items/3016607078-lego-creator-ref-31087",
    "published": 1684006935,
    "uuid": "eda2cc6c-59df-4802-bc8b-2553176b1d46"
  },
  {
    "id": "31087",
    "title": "LEGO set 31087",
    "price": 5.95,
    "link": "https://www.vinted.fr/items/4904852574-lego-set-31087",
    "published": 1724004792,
    "uuid": "316ba475-c6a2-4477-a608-78d1741f0985"
  },
  {
    "id": "31087",
    "title": "Lego creator 31087",
    "price": 16.45,
    "link": "https://www.vinted.fr/items/4003170911-lego-creator-31087",
    "published": 1705786552,
    "uuid": "f3e38bdd-e054-4e20-b167-c682191bf63e"
  },
  {
    "id": "31087",
    "title": "Lego creator 3 in 1 31087",
    "price": 13.3,
    "link": "https://www.vinted.fr/items/3765348497-lego-creator-3-in-1-31087",
    "published": 1700080978,
    "uuid": "9c92b2a9-8d9e-4d4e-a2be-b32831601e73"
  },
  {
    "id": "31087",
    "title": "Lego Creator 31087",
    "price": 9.63,
    "link": "https://www.vinted.fr/items/5320554026-lego-creator-31087",
    "published": 1730626095,
    "uuid": "efb5516f-8468-4e18-a3de-1aae7d14c195"
  },
  {
    "id": "31087",
    "title": "Lego Creator 31087",
    "price": 21.7,
    "link": "https://www.vinted.fr/items/2803762185-lego-creator-31087",
    "published": 1679175464,
    "uuid": "a3f77572-cb6b-4e64-90f9-6970032315ea"
  },
  {
    "id": "31087",
    "title": "Lego 31087 Creator 3 in 1 Set Strandbuggy",
    "price": 10.15,
    "link": "https://www.vinted.fr/items/4231116415-lego-31087-creator-3-in-1-set-strandbuggy",
    "published": 1710605927,
    "uuid": "8a066196-67fa-466f-925f-dfc040d99b98"
  },
  {
    "id": "31087",
    "title": "Lego 31087 Le buggy des dunes",
    "price": 3.85,
    "link": "https://www.vinted.fr/items/1321731188-lego-31087-le-buggy-des-dunes",
    "published": 1632481672,
    "uuid": "d4ca3dc5-673c-4154-9c0f-b086c714da1d"
  },
  {
    "id": "31087",
    "title": "Lego creator 31087",
    "price": 9.1,
    "link": "https://www.vinted.fr/items/1615033119-lego-creator-31087",
    "published": 1644163578,
    "uuid": "733eebf6-68c2-475a-84a2-66005c8718af"
  },
  {
    "id": "31087",
    "title": "Lot 3 sets de Lego Creator « 3 en 1 »",
    "price": 26.95,
    "link": "https://www.vinted.fr/items/5296906484-lot-3-sets-de-lego-creator-3-en-1",
    "published": 1730201237,
    "uuid": "10e4eec0-4a25-48a3-a171-640aff32f9ba"
  },
  {
    "id": "31087",
    "title": "Lego creator 31087",
    "price": 8.58,
    "link": "https://www.vinted.fr/items/4618508157-lego-creator-31087",
    "published": 1717936788,
    "uuid": "ba6a8a20-5784-4c0e-ae17-ff03838ccac2"
  },
  {
    "id": "31087",
    "title": "Lego creator lot.",
    "price": 21.7,
    "link": "https://www.vinted.fr/items/4751540371-lego-creator-lot",
    "published": 1720697547,
    "uuid": "ec0388ca-f84a-41e9-85b6-f01e44051019"
  },
  {
    "id": "31087",
    "title": "Lego creator",
    "price": 14.35,
    "link": "https://www.vinted.fr/items/3613611783-lego-creator",
    "published": 1697383449,
    "uuid": "b4ef7f0e-0a97-4684-8aa7-5a220b648d2b"
  },
  {
    "id": "31087",
    "title": "Lego creator 31087 buggy",
    "price": 8.05,
    "link": "https://www.vinted.fr/items/4483602953-lego-creator-31087-buggy",
    "published": 1715335229,
    "uuid": "9744bd7e-f947-4ab9-b41d-9609f9138a81"
  },
  {
    "id": "31087",
    "title": "LEGO 31087 3 en 1  3ans et +",
    "price": 11.1,
    "link": "https://www.vinted.fr/items/3630878098-lego-31087-3-en-1-3ans-et",
    "published": 1703149523,
    "uuid": "8a3ac99f-f9d5-4476-b5c8-019116bfb992"
  },
  {
    "id": "31087",
    "title": "Lego Creator 3 in 1 set 31087",
    "price": 9.1,
    "link": "https://www.vinted.fr/items/3121454769-lego-creator-3-in-1-set-31087",
    "published": 1686413866,
    "uuid": "662a5785-a2a4-4458-8c90-3fab5c2a80e2"
  },
  {
    "id": "31087",
    "title": "Lego Creator 31087",
    "price": 16.45,
    "link": "https://www.vinted.fr/items/3788062748-lego-creator-31087",
    "published": 1700507398,
    "uuid": "0983590b-2959-469e-a781-f97abbc907ff"
  },
  {
    "id": "31087",
    "title": "Lego 31087 Le buggy des dunes",
    "price": 16.45,
    "link": "https://www.vinted.fr/items/2267434978-lego-31087-le-buggy-des-dunes",
    "published": 1664722144,
    "uuid": "76472e1d-c7ba-4e2c-8542-f246e0ae113a"
  },
  {
    "id": "31087",
    "title": "Lego creator - 31087 - le buggy des dunes",
    "price": 13.3,
    "link": "https://www.vinted.fr/items/5077710873-lego-creator-31087-le-buggy-des-dunes",
    "published": 1726851036,
    "uuid": "92fcfab4-36c4-434e-83db-ddcdf9572d2d"
  },
  {
    "id": "31087",
    "title": "Lego creator codice 31087",
    "price": 11.2,
    "link": "https://www.vinted.fr/items/2393965813-lego-creator-codice-31087",
    "published": 1667846361,
    "uuid": "f252fd12-dbc8-4159-a8bb-20984d63541d"
  },
  {
    "id": "31087",
    "title": "lot 2 Lego 31087 et 60213",
    "price": 13.3,
    "link": "https://www.vinted.fr/items/4206424666-lot-2-lego-31087-et-60213",
    "published": 1710086650,
    "uuid": "6efa3847-608d-43c3-bfb1-34322defc88b"
  },
  {
    "id": "31087",
    "title": "LEGO Creator - Dune Buggy 3 in 1",
    "price": 16.45,
    "link": "https://www.vinted.fr/items/3711789890-lego-creator-dune-buggy-3-in-1",
    "published": 1699121024,
    "uuid": "94cdde87-ce1a-43f4-a725-9b793c134e2e"
  },
  {
    "id": "31087",
    "title": "Lego 31087 creator 3 en 1",
    "price": 16.45,
    "link": "https://www.vinted.fr/items/2459858389-lego-31087-creator-3-en-1",
    "published": 1669548316,
    "uuid": "39065c05-852b-49b6-b8ed-f5429bd99686"
  },
  {
    "id": "31087",
    "title": "Lego 31087",
    "price": 16.45,
    "link": "https://www.vinted.fr/items/5317293561-lego-31087",
    "published": 1730558328,
    "uuid": "022d4433-1231-45fb-a48a-3a950572f8f7"
  },
  {
    "id": "31087",
    "title": "Vend lego creator",
    "price": 20.65,
    "link": "https://www.vinted.fr/items/4520997712-vend-lego-creator",
    "published": 1716050896,
    "uuid": "907d9322-e1e5-40c5-bb93-2e2d614ec1c3"
  },
  {
    "id": "31087",
    "title": "Lot de 2 Lego creator 3 en 1 : 31087 et 31071",
    "price": 17.5,
    "link": "https://www.vinted.fr/items/5319800192-lot-de-2-lego-creator-3-en-1-31087-et-31071",
    "published": 1730587514,
    "uuid": "c9c8ad86-e306-4f06-b584-90ad65e92e79"
  },
  {
    "id": "31087",
    "title": "Lego 3 en 1  31087",
    "price": 17.5,
    "link": "https://www.vinted.fr/items/5182503588-lego-3-en-1-31087",
    "published": 1728398188,
    "uuid": "d19346ad-6b05-42ec-9e1f-8af7230f2b63"
  },
  {
    "id": "31087",
    "title": "Lego Creator 3 in 1   31087",
    "price": 11.2,
    "link": "https://www.vinted.fr/items/3714849987-lego-creator-3-in-1-31087",
    "published": 1699185973,
    "uuid": "03e9b310-71ec-46c8-8389-06e6d414c587"
  },
  {
    "id": "31087",
    "title": "Lego creator 31087",
    "price": 13.3,
    "link": "https://www.vinted.fr/items/1937894512-lego-creator-31087",
    "published": 1654436007,
    "uuid": "7a6bcbb2-821f-46e9-b59e-99397d277102"
  },
  {
    "id": "31087",
    "title": "LEGO® Creator 3 en 1 - 31087 - Le buggy des dunes",
    "price": 4.9,
    "link": "https://www.vinted.fr/items/2650528264-legor-creator-3-en-1-31087-le-buggy-des-dunes",
    "published": 1675330563,
    "uuid": "82ebd4d5-0077-48dd-a4c6-68d07b03e6ef"
  },
  {
    "id": "31087",
    "title": "Lego creator 31087",
    "price": 10.15,
    "link": "https://www.vinted.fr/items/2591219711-lego-creator-31087",
    "published": 1673784218,
    "uuid": "8c9d4c51-0a50-43e2-9fa2-8c2afc966bcc"
  },
  {
    "id": "31087",
    "title": "Lego Creator 31087",
    "price": 13.3,
    "link": "https://www.vinted.fr/items/2287694451-lego-creator-31087",
    "published": 1665239340,
    "uuid": "d09baa74-e5c8-43fe-8f1d-f625493626e0"
  },
  {
    "id": "31087",
    "title": "31087 neu lego strandbuggy",
    "price": 31.15,
    "link": "https://www.vinted.fr/items/5261846875-31087-neu-lego-strandbuggy",
    "published": 1729612819,
    "uuid": "43a6ee97-7308-44a1-97b3-05727de3a4aa"
  },
  {
    "id": "31087",
    "title": "Notice livret Lego Creator 31087 Véhicule tout terrain  ",
    "price": 2.8,
    "link": "https://www.vinted.fr/items/3530966683-notice-livret-lego-creator-31087-vehicule-tout-terrain",
    "published": 1695820938,
    "uuid": "51af4d82-8f58-42d6-a744-fe27d69cfae2"
  },
  {
    "id": "31087",
    "title": "Set Lego 31087",
    "price": 16.45,
    "link": "https://www.vinted.fr/items/3457043717-set-lego-31087",
    "published": 1694361308,
    "uuid": "10424b21-2406-43d9-aa1c-4261e91adc12"
  },
  {
    "id": "31087",
    "title": "Lego Creator #lego #legocreator #31087",
    "price": 13.3,
    "link": "https://www.vinted.fr/items/4893210257-lego-creator-lego-legocreator-31087",
    "published": 1727779007,
    "uuid": "c51f12e5-99fa-4986-a465-86f5649e0f5b"
  },
  {
    "id": "31087",
    "title": "Lego Creator pakket",
    "price": 24.33,
    "link": "https://www.vinted.fr/items/5320701142-lego-creator-pakket",
    "published": 1730627352,
    "uuid": "ab9f503d-0e29-4088-ba46-f9d334292bf1"
  },
  {
    "id": "31087",
    "title": "Lego creator 3 in 1, 31087, Autos, Flugzeug, vollständig",
    "price": 10.15,
    "link": "https://www.vinted.fr/items/5218234671-lego-creator-3-in-1-31087-autos-flugzeug-vollstandig",
    "published": 1728926824,
    "uuid": "6bc95b0c-bdc9-466e-a97f-3248af021c93"
  },
  {
    "id": "31087",
    "title": "Lego 31087 le buggy des dunes",
    "price": 21.7,
    "link": "https://www.vinted.fr/items/4290460558-lego-31087-le-buggy-des-dunes",
    "published": 1711748150,
    "uuid": "021d5f24-1006-4044-8498-3b8cb503e09b"
  },
  {
    "id": "31087",
    "title": "Lego Creator 31087 - 3 en 1 Buggy Quad Avion",
    "price": 11.2,
    "link": "https://www.vinted.fr/items/5243992084-lego-creator-31087-3-en-1-buggy-quad-avion",
    "published": 1729355439,
    "uuid": "675488a5-8dbb-40c2-b8bc-4f3fcf839dc0"
  },
  {
    "id": "31087",
    "title": "Lego Creator 3 in , Strand Buggy 31087, Neu und OVP",
    "price": 17.5,
    "link": "https://www.vinted.fr/items/4971581057-lego-creator-3-in-strand-buggy-31087-neu-und-ovp",
    "published": 1725199950,
    "uuid": "1463306f-287b-4e53-88a5-cca05602d0ed"
  },
  {
    "id": "31087",
    "title": "Lego creator 31087 Strandbuggy",
    "price": 13.83,
    "link": "https://www.vinted.fr/items/3480733971-lego-creator-31087-strandbuggy",
    "published": 1694880770,
    "uuid": "c2704af8-3bba-488c-bcf8-4068e8ee74a6"
  },
  {
    "id": "31087",
    "title": "Lego creator 31087 le buggy des dunes",
    "price": 16.45,
    "link": "https://www.vinted.fr/items/5316400829-lego-creator-31087-le-buggy-des-dunes",
    "published": 1730552113,
    "uuid": "2a829847-a7a5-427b-bf66-1067c4e92a6e"
  },
  {
    "id": "31087",
    "title": "Lego creator 3 in 1 31087",
    "price": 13.83,
    "link": "https://www.vinted.fr/items/2068461732-lego-creator-3-in-1-31087",
    "published": 1659118420,
    "uuid": "658dda40-2471-4dc2-a339-4d3af5525a41"
  },
  {
    "id": "31087",
    "title": "Lego Creator 31087, 3 in 1, (6+)",
    "price": 13.3,
    "link": "https://www.vinted.fr/items/2254957607-lego-creator-31087-3-in-1-6",
    "published": 1664450370,
    "uuid": "33cfe1ca-9316-4a38-b197-52bd95a30c8e"
  },
  {
    "id": "31087",
    "title": "Lego Creator 3in1 Flieger Safari-Truck 31087",
    "price": 11.2,
    "link": "https://www.vinted.fr/items/3789614064-lego-creator-3in1-flieger-safari-truck-31087",
    "published": 1700560718,
    "uuid": "2e92c666-9eff-4d25-a027-c6f3e81de6df"
  },
  {
    "id": "31087",
    "title": "Lego Creator 31087",
    "price": 7.53,
    "link": "https://www.vinted.fr/items/1675672930-lego-creator-31087",
    "published": 1646570625,
    "uuid": "edbc453c-ee24-4a34-b5c4-19423f8e8fa3"
  },
  {
    "id": "31087",
    "title": "LEGO | Creator 3-in-1 | 31087 | Dune buggy",
    "price": 8.58,
    "link": "https://www.vinted.fr/items/5336331552-lego-creator-3-in-1-31087-dune-buggy",
    "published": 1730840554,
    "uuid": "c65b8235-d82e-4fa5-a000-e896e9966c6d"
  },
  {
    "id": "31087",
    "title": "Lego 31087 creator 3 en 1 ",
    "price": 21.7,
    "link": "https://www.vinted.fr/items/3612245380-lego-31087-creator-3-en-1",
    "published": 1697374878,
    "uuid": "7340db08-3e6a-4b1e-801a-33429fb17ad1"
  },
  {
    "id": "31087",
    "title": "Lego Creator 3 en 1 31087 ",
    "price": 5.95,
    "link": "https://www.vinted.fr/items/1163549495-lego-creator-3-en-1-31087",
    "published": 1623357796,
    "uuid": "86343c4b-600c-44d5-a188-672c59cd79b6"
  },
  {
    "id": "31087",
    "title": "Lego creatore- le buggy des dunes - 31087",
    "price": 11.2,
    "link": "https://www.vinted.fr/items/2260576327-lego-creatore-le-buggy-des-dunes-31087",
    "published": 1664609189,
    "uuid": "127b6c5d-e31e-4bd4-aa6d-a9e19927a642"
  },
  {
    "id": "31087",
    "title": "Légo Creator 3 en 1: le buggy des dunes 31087",
    "price": 26.95,
    "link": "https://www.vinted.fr/items/4743869689-lego-creator-3-en-1-le-buggy-des-dunes-31087",
    "published": 1720532432,
    "uuid": "f05779e7-c742-44f2-b34a-8120cac6062d"
  },
  {
    "id": "31087",
    "title": "Lego creator 3en1 31087",
    "price": 18.66,
    "link": "https://www.vinted.fr/items/5305334165-lego-creator-3en1-31087",
    "published": 1730329080,
    "uuid": "31672f06-f49c-4dce-8b09-9fd3099a6bd6"
  },
  {
    "id": "31087",
    "title": "Lot vrac Lego ",
    "price": 22.75,
    "link": "https://www.vinted.fr/items/1794849774-lot-vrac-lego",
    "published": 1651151685,
    "uuid": "5b1b4be0-2fe5-438d-9061-67fd34a5b1b3"
  },
  {
    "id": "31087",
    "title": "Lego Creator",
    "price": 19.6,
    "link": "https://www.vinted.fr/items/2447889091-lego-creator",
    "published": 1669204693,
    "uuid": "b7bfccfa-9242-422b-99c4-5499c630f3c9"
  },
  {
    "id": "31087",
    "title": "Lego creator dune buggy 31087",
    "price": 11.2,
    "link": "https://www.vinted.fr/items/4245399872-lego-creator-dune-buggy-31087",
    "published": 1710863167,
    "uuid": "4bf04afa-f37a-447c-8e61-d7e209315884"
  },
  {
    "id": "31087",
    "title": "LEGO® Creator 3-in-1 Strandbuggy",
    "price": 16.45,
    "link": "https://www.vinted.fr/items/2887735641-legor-creator-3-in-1-strandbuggy",
    "published": 1681145957,
    "uuid": "dc6fe6bb-0f50-4875-bfc7-f26eebf054d9"
  },
  {
    "id": "31087",
    "title": "Lego Creator 31087",
    "price": 16.45,
    "link": "https://www.vinted.fr/items/3459814225-lego-creator-31087",
    "published": 1694432131,
    "uuid": "fc9a01fc-02d0-4179-9781-899c189d520f"
  },
  {
    "id": "31087",
    "title": "Lego Creator 3 in 1 - Dune Buggy, Aereo, Quad (31087)",
    "price": 13.3,
    "link": "https://www.vinted.fr/items/4007346841-lego-creator-3-in-1-dune-buggy-aereo-quad-31087",
    "published": 1705860190,
    "uuid": "bfcc9af0-7fb1-4483-8d7e-652bb41bb608"
  },
  {
    "id": "31087",
    "title": "Lego creator 31087 Dune buggy",
    "price": 12.25,
    "link": "https://www.vinted.fr/items/2791590889-lego-creator-31087-dune-buggy",
    "published": 1678883512,
    "uuid": "a1af9fad-ee6a-4644-bc82-0de7345bd400"
  },
  {
    "id": "31087",
    "title": "Lego 3 in 1 - Creator n.31087",
    "price": 10.15,
    "link": "https://www.vinted.fr/items/1953197750-lego-3-in-1-creator-n31087",
    "published": 1654874704,
    "uuid": "6fe8c936-512a-4b9a-a803-c8d5d23236f3"
  },
  {
    "id": "31087",
    "title": "Lego creator  le buggy des dunes 31087",
    "price": 18.55,
    "link": "https://www.vinted.fr/items/2414479339-lego-creator-le-buggy-des-dunes-31087",
    "published": 1668359208,
    "uuid": "0b7554f1-505d-422d-bbb9-07877932e7b1"
  },
  {
    "id": "31087",
    "title": "Lego 31087 Dune Buggy",
    "price": 19.6,
    "link": "https://www.vinted.fr/items/3736174902-lego-31087-dune-buggy",
    "published": 1699555223,
    "uuid": "56eeb3ea-dbe6-4c18-a051-275719c95abc"
  },
  {
    "id": "31087",
    "title": "Lego Créator 3 en 1. 31087. Très bon état. Complet",
    "price": 8.58,
    "link": "https://www.vinted.fr/items/1061263147-lego-creator-3-en-1-31087-tres-bon-etat-complet",
    "published": 1623224931,
    "uuid": "e642bd57-88cc-498a-b631-b4d77dd1b365"
  },
  {
    "id": "31087",
    "title": "buggy des dunes LEGO® Creator 31087",
    "price": 16.45,
    "link": "https://www.vinted.fr/items/3014074408-buggy-des-dunes-legor-creator-31087",
    "published": 1683972553,
    "uuid": "75e49a9e-4c18-4c3c-8c51-5ba90129b840"
  },
  {
    "id": "31087",
    "title": "Lego creator 3 en 1 6 ans 31087 Le buggy des dunes",
    "price": 23.8,
    "link": "https://www.vinted.fr/items/3434248061-lego-creator-3-en-1-6-ans-31087-le-buggy-des-dunes",
    "published": 1693831838,
    "uuid": "e660189a-90b4-4ad5-90b4-72f9df600346"
  },
  {
    "id": "31087",
    "title": "Lego 31087 neuf ",
    "price": 26.95,
    "link": "https://www.vinted.fr/items/2499971484-lego-31087-neuf",
    "published": 1670686083,
    "uuid": "5a2235a5-efc8-42e5-bbc5-696132fcde96"
  },
  {
    "id": "31087",
    "title": "LEGO Le buggy des dunes 3 en 1",
    "price": 21.7,
    "link": "https://www.vinted.fr/items/5171688944-lego-le-buggy-des-dunes-3-en-1",
    "published": 1728233002,
    "uuid": "50bb8a49-6028-4467-bc7e-6041903ae604"
  },
  {
    "id": "31087",
    "title": "Lego Creator ",
    "price": 26.95,
    "link": "https://www.vinted.fr/items/4059944477-lego-creator",
    "published": 1707045280,
    "uuid": "1b1c1d99-602f-40b7-9308-bd500db71540"
  },
  {
    "id": "31087",
    "title": "Lego Creator 31087, dume buggy",
    "price": 26.95,
    "link": "https://www.vinted.fr/items/5324952456-lego-creator-31087-dume-buggy",
    "published": 1730653613,
    "uuid": "af8a3e37-a6b2-491a-8841-29230e454704"
  },
  {
    "id": "31087",
    "title": "Lot Lego creator 31101 et 31087 neuf",
    "price": 52.15,
    "link": "https://www.vinted.fr/items/5326861585-lot-lego-creator-31101-et-31087-neuf",
    "published": 1730672613,
    "uuid": "a84da9d4-97ca-4bf5-9109-a18b5dfd9baf"
  },
  {
    "id": "31087",
    "title": "Lot de Lego",
    "price": 58.45,
    "link": "https://www.vinted.fr/items/4772520620-lot-de-lego",
    "published": 1721139253,
    "uuid": "ebedc48b-3525-41c5-9390-83c28430ea98"
  },
  {
    "id": "31087",
    "title": "Lego Creator 31087",
    "price": 11.2,
    "link": "https://www.vinted.fr/items/1281714875-lego-creator-31087",
    "published": 1630238513,
    "uuid": "88f993c9-53a1-4a99-b087-8c98520a8a6b"
  },
  {
    "id": "31087",
    "title": "Lego creator 3en1 31087 Le buggy des dunes",
    "price": 19.6,
    "link": "https://www.vinted.fr/items/1499609993-lego-creator-3en1-31087-le-buggy-des-dunes",
    "published": 1639053024,
    "uuid": "f681ba00-e141-413f-8524-a121557c403e"
  },
  {
    "id": "31087",
    "title": "Lego City",
    "price": 42.7,
    "link": "https://www.vinted.fr/items/4549010645-lego-city",
    "published": 1716566843,
    "uuid": "f25b1b16-2de8-404c-b923-007d4706fe8c"
  },
  {
    "id": "31087",
    "title": "Lot de lego city",
    "price": 26.95,
    "link": "https://www.vinted.fr/items/2039967561-lot-de-lego-city",
    "published": 1658044331,
    "uuid": "ffbb0847-7961-4797-b76b-ebcf1171e830"
  },
  {
    "id": "31087",
    "title": "Lego creator 31087",
    "price": 9.1,
    "link": "https://www.vinted.fr/items/724002393-lego-creator-31087",
    "published": 1605295088,
    "uuid": "a3152e51-5700-4e31-8e07-db1d51866d5a"
  },
  {
    "id": "31087",
    "title": "Lego set 31087",
    "price": 22.75,
    "link": "https://www.vinted.fr/items/2399599158-lego-set-31087",
    "published": 1668004950,
    "uuid": "273d9a28-f81d-4aca-91b7-bdaf53a21286"
  },
  {
    "id": "31087",
    "title": "Lot Lego très complet avec notices ",
    "price": 84.7,
    "link": "https://www.vinted.fr/items/3716985428-lot-lego-tres-complet-avec-notices",
    "published": 1700430419,
    "uuid": "cca55283-e083-4a9f-bf8e-ac5a65295b82"
  },
  {
    "id": "31087",
    "title": "Kg di Lego di tutti i tipi",
    "price": 555.9,
    "link": "https://www.vinted.fr/items/3176959770-kg-di-lego-di-tutti-i-tipi",
    "published": 1687776784,
    "uuid": "31370723-6e0b-4038-96a1-cc0554442452"
  }
]