[
  {
    "id": "43249",
    "title": "Lego Stitch Disney 43249",
    "price": 51.1,
    "link": "https://www.vinted.fr/items/5434888657-lego-stitch-disney-43249",
    "published": 1732457330,
    "uuid": "9417d700-bb17-42fe-ba74-283594597e84"
  },
  {
    "id": "43249",
    "title": "Juego de construcción Lego Disney Stitch 43249",
    "price": 52.15,
    "link": "https://www.vinted.fr/items/5360966820-juego-de-construccion-lego-disney-stitch-43249",
    "published": 1731260165,
    "uuid": "cb4ad28d-2811-4de9-955b-a46dec5557c4"
  },
  {
    "id": "43249",
    "title": "Lego stitch neuf",
    "price": 52.68,
    "link": "https://www.vinted.fr/items/5422252292-lego-stitch-neuf",
    "published": 1732262573,
    "uuid": "39767dc9-c62b-405d-9308-782fdf2713b1"
  },
  {
    "id": "43249",
    "title": "Lego 43249 stich",
    "price": 58.45,
    "link": "https://www.vinted.fr/items/5411033171-lego-43249-stich",
    "published": 1732041377,
    "uuid": "a72365ed-96b4-4b66-b1fc-2a53d8315c36"
  },
  {
    "id": "43249",
    "title": "Lego 43249 STITCH neuf",
    "price": 59.5,
    "link": "https://www.vinted.fr/items/5411614064-lego-43249-stitch-neuf",
    "published": 1732047914,
    "uuid": "4b69b3a9-4c75-4c16-8972-02b1acea1177"
  },
  {
    "id": "43249",
    "title": "Lego 43249",
    "price": 52.15,
    "link": "https://www.vinted.fr/items/5431241154-lego-43249",
    "published": 1732394094,
    "uuid": "cb487d46-bc4c-46f3-afb3-d97cb6b16171"
  },
  {
    "id": "43249",
    "title": "lego stitch disney",
    "price": 58.45,
    "link": "https://www.vinted.fr/items/5414364563-lego-stitch-disney",
    "published": 1732110472,
    "uuid": "f01ebdb1-2ee7-403a-b903-49be49894140"
  },
  {
    "id": "43249",
    "title": "Lego 43249 Disney Stitch Nuovo",
    "price": 58.45,
    "link": "https://www.vinted.fr/items/5399897049-lego-43249-disney-stitch-nuovo",
    "published": 1731864448,
    "uuid": "f2d0a0f2-175d-444e-9f91-8b1ce189272d"
  },
  {
    "id": "43249",
    "title": "Lego 43249 stich neuf",
    "price": 58.45,
    "link": "https://www.vinted.fr/items/5424119282-lego-43249-stich-neuf",
    "published": 1732285153,
    "uuid": "9f570808-21ce-4f28-926d-4e16bdb86637"
  },
  {
    "id": "43249",
    "title": "Lego Disney 43249 stitch neuf",
    "price": 58.45,
    "link": "https://www.vinted.fr/items/5432079961-lego-disney-43249-stitch-neuf",
    "published": 1732436794,
    "uuid": "0bc359ba-6d65-44cd-adeb-12203716bc59"
  },
  {
    "id": "43249",
    "title": "Lego Stitch 43249",
    "price": 58.45,
    "link": "https://www.vinted.fr/items/5353826285-lego-stitch-43249",
    "published": 1731168612,
    "uuid": "2eb7e9b2-d7f2-4cd7-9401-d5e4473463cd"
  },
  {
    "id": "43249",
    "title": "Lego Disney 43249 Stitch",
    "price": 61.6,
    "link": "https://www.vinted.fr/items/5378905732-lego-disney-43249-stitch",
    "published": 1731528830,
    "uuid": "6a0c6d86-8dc3-4cd9-932a-c0095af2c354"
  },
  {
    "id": "43249",
    "title": "LEGO 43249 Stitch lilo disney Expert Nuovo *A",
    "price": 63.7,
    "link": "https://www.vinted.fr/items/5092349162-lego-43249-stitch-lilo-disney-expert-nuovo-a",
    "published": 1727068869,
    "uuid": "d4791e4a-02f7-40ad-9433-48bec0d45578"
  },
  {
    "id": "43249",
    "title": "Lego 43249",
    "price": 58.45,
    "link": "https://www.vinted.fr/items/5419062418-lego-43249",
    "published": 1732194335,
    "uuid": "15d24a8c-cce8-4c4a-be40-dcce1ebc23d2"
  },
  {
    "id": "43249",
    "title": "Lego Stitch",
    "price": 58.45,
    "link": "https://www.vinted.fr/items/5425687187-lego-stitch",
    "published": 1732304224,
    "uuid": "99002479-73fb-4c74-a3e9-f4c2fe9f114d"
  },
  {
    "id": "43249",
    "title": "Lego Stich 43249",
    "price": 63.7,
    "link": "https://www.vinted.fr/items/5317747881-lego-stich-43249",
    "published": 1730561732,
    "uuid": "bb0bd37b-5ce4-493c-bd4a-31b7fe6432a0"
  },
  {
    "id": "43249",
    "title": "Lego - Disney Stitch 43249",
    "price": 62.65,
    "link": "https://www.vinted.fr/items/5415399186-lego-disney-stitch-43249",
    "published": 1732120026,
    "uuid": "d897e07a-9215-4d21-bf18-114bedcdafe2"
  },
  {
    "id": "43249",
    "title": "43249 - Stitch",
    "price": 62.65,
    "link": "https://www.vinted.fr/items/5326254115-43249-stitch",
    "published": 1730664415,
    "uuid": "b11cff76-98c4-4c36-9af8-eab8fe1540fa"
  },
  {
    "id": "43249",
    "title": "Lego Stitch 43249 neuf",
    "price": 63.7,
    "link": "https://www.vinted.fr/items/5423164091-lego-stitch-43249-neuf",
    "published": 1732274805,
    "uuid": "4cdb6c68-56ea-41d8-af75-fdfc826b7d08"
  },
  {
    "id": "43249",
    "title": "Lego 43249 Stitch nuovo mai aperto 60€",
    "price": 63.7,
    "link": "https://www.vinted.fr/items/4935132997-lego-43249-stitch-nuovo-mai-aperto-60eu",
    "published": 1724581308,
    "uuid": "e90ef1c0-ac8a-493e-8f4d-4c40df6df49b"
  },
  {
    "id": "43249",
    "title": "Lego Stitch 43249",
    "price": 95.2,
    "link": "https://www.vinted.fr/items/4192338210-lego-stitch-43249",
    "published": 1709810421,
    "uuid": "4e97540a-b63c-48e4-ab7e-04b2a58435ed"
  },
  {
    "id": "43249",
    "title": "Lego 43249",
    "price": 74.2,
    "link": "https://www.vinted.fr/items/5359129141-lego-43249",
    "published": 1731248919,
    "uuid": "90d62f54-dee4-4c60-aebc-48054b38dc52"
  },
  {
    "id": "43249",
    "title": "Lego 43249 stitch / Brickh’eadz  / Lego stitch disney",
    "price": 68.95,
    "link": "https://www.vinted.fr/items/4377227113-lego-43249-stitch-brickheadz-lego-stitch-disney",
    "published": 1713357562,
    "uuid": "75337447-db5e-43b3-95e0-e4be743a4813"
  },
  {
    "id": "43249",
    "title": "Lego 43249 STITCH",
    "price": 63.7,
    "link": "https://www.vinted.fr/items/4986816948-lego-43249-stitch",
    "published": 1725460366,
    "uuid": "31f7a2dc-f29f-465b-b1dd-fb6d3d8d81b8"
  },
  {
    "id": "43249",
    "title": "Lego Stitch 43249",
    "price": 63.7,
    "link": "https://www.vinted.fr/items/4453244645-lego-stitch-43249",
    "published": 1714766533,
    "uuid": "3019edcf-ccf7-49ca-a2b8-86dc51a009ec"
  },
  {
    "id": "43249",
    "title": "Lego Stitch 43249",
    "price": 95.2,
    "link": "https://www.vinted.fr/items/4288457380-lego-stitch-43249",
    "published": 1711720736,
    "uuid": "7208f26a-f487-4dbf-ad3e-cf5122a12bc3"
  },
  {
    "id": "43249",
    "title": "LEGO 43249 - Stitch Disney Classic",
    "price": 74.15,
    "link": "https://www.vinted.fr/items/4628725658-lego-43249-stitch-disney-classic",
    "published": 1718113893,
    "uuid": "7242d917-eb24-4997-bcb8-6d17b07934b0"
  }
]